README.md
setup.cfg
setup.py
sickdb_client/__init__.py
sickdb_client.egg-info/PKG-INFO
sickdb_client.egg-info/SOURCES.txt
sickdb_client.egg-info/dependency_links.txt
sickdb_client.egg-info/requires.txt
sickdb_client.egg-info/top_level.txt
tests/__init__.py
tests/test_client_request_params.py