Metadata-Version: 1.0
Name: sickdb-client
Version: 0.1
Summary: Python Client For SickDB's API
Home-page: http://globally.ltd
Author: gltd
Author-email: dev@globally.ltd
License: UNKNOWN
Platform: UNKNOWN
